{
  "ts": 1765473359051,
  "items": [
    {
      "title": "How technology is changing modern solar O&#038;M",
      "url": "https://www.pv-magazine.com/2025/12/11/pv-week-europe-2025-operations-maintenance-solar-conference-session-recording/",
      "date": "2025-12-11T16:55:43.000Z",
      "source": "PV Magazine (Markets & Policy)",
      "bucket": "A"
    },
    {
      "title": "US space solar startup proves wireless power system works in motion",
      "url": "https://www.pv-magazine.com/2025/12/11/overview-energy-united-states-space-solar-power-beaming-satellite-system/",
      "date": "2025-12-11T16:30:27.000Z",
      "source": "PV Magazine (Markets & Policy)",
      "bucket": "A"
    },
    {
      "title": "Cambridge startup targets 15% module efficiency gain",
      "url": "https://www.pv-magazine.com/2025/12/11/cambridge-startup-targets-15-module-efficiency-gain/",
      "date": "2025-12-11T16:15:24.000Z",
      "source": "PV Magazine (Markets & Policy)",
      "bucket": "A"
    },
    {
      "title": "Brazil to add 11.4 GW of solar in 2025 despite regulatory hurdles",
      "url": "https://www.pv-magazine.com/2025/12/11/brazil-to-add-11-4-gw-of-solar-in-2025-despite-regulatory-hurdles/",
      "date": "2025-12-11T16:00:23.000Z",
      "source": "PV Magazine (Markets & Policy)",
      "bucket": "A"
    },
    {
      "title": "New all-aluminum solar carport from France",
      "url": "https://www.pv-magazine.com/2025/12/11/new-all-aluminum-solar-carport-from-france/",
      "date": "2025-12-11T15:30:55.000Z",
      "source": "PV Magazine (Markets & Policy)",
      "bucket": "A"
    },
    {
      "title": "Bangladesh reinstates 11 solar plants totaling 918 MW after tariff cuts",
      "url": "https://www.pv-magazine.com/2025/12/11/bangladesh-reinstates-11-solar-plants-totaling-918-mw-after-tariff-cuts/",
      "date": "2025-12-11T15:30:20.000Z",
      "source": "PV Magazine (Markets & Policy)",
      "bucket": "A"
    },
    {
      "title": "How distributed energy resources could combat soaring electricity costs in the US",
      "url": "https://www.energy-storage.news/how-distributed-energy-resources-could-combat-soaring-electricity-costs-in-the-us/",
      "date": "2025-12-11T15:16:02.000Z",
      "source": "Energy Storage News",
      "bucket": "A"
    },
    {
      "title": "Trina Solar to invest in Holosolis PV gigafactory in France",
      "url": "https://www.pv-magazine.com/2025/12/11/trina-solar-to-invest-in-holosolis-pv-gigafactory-in-france/",
      "date": "2025-12-11T14:48:52.000Z",
      "source": "PV Magazine (Markets & Policy)",
      "bucket": "A"
    },
    {
      "title": "India’s Trontek enters home storage market with new lithium systems",
      "url": "https://www.pv-magazine.com/2025/12/11/indias-trontek-enters-home-storage-market-with-new-lithium-systems/",
      "date": "2025-12-11T13:45:31.000Z",
      "source": "PV Magazine (Markets & Policy)",
      "bucket": "A"
    },
    {
      "title": "US BESS deals: Samsung SDI&#8217;s first LFP contract, Trina&#8217;s 1GWh+ agreement with Lightshift",
      "url": "https://www.energy-storage.news/us-bess-deals-samsung-sdis-first-lfp-contract-trinas-1gwh-agreement-with-lightshift/",
      "date": "2025-12-11T12:20:16.000Z",
      "source": "Energy Storage News",
      "bucket": "A"
    },
    {
      "title": "EU installs 65.1 GW of solar in 2025",
      "url": "https://www.pv-magazine.com/2025/12/11/eu-installs-65-1-gw-of-solar-in-2025/",
      "date": "2025-12-11T12:15:58.000Z",
      "source": "PV Magazine (Markets & Policy)",
      "bucket": "A"
    },
    {
      "title": "Great British Energy doubles fund, commits $1.3 billion for manufacturing",
      "url": "https://www.pv-magazine.com/2025/12/11/great-british-energy-doubles-fund-commits-1-3-billion-for-manufacturing/",
      "date": "2025-12-11T12:00:35.000Z",
      "source": "PV Magazine (Markets & Policy)",
      "bucket": "A"
    },
    {
      "title": "Eternal Sun offers solar simulators for space PV testing",
      "url": "https://www.pv-magazine.com/2025/12/11/eternal-sun-offers-solar-simulators-for-space-pv-testing/",
      "date": "2025-12-11T11:57:29.000Z",
      "source": "PV Magazine (Markets & Policy)",
      "bucket": "A"
    },
    {
      "title": "Germany firmly enters large-scale BESS era with EnBW, Vattenfall and Enertrag project news",
      "url": "https://www.energy-storage.news/germany-firmly-enters-large-scale-bess-era-with-enbw-vattenfall-and-enertrag-project-news/",
      "date": "2025-12-11T11:37:53.000Z",
      "source": "Energy Storage News",
      "bucket": "A"
    },
    {
      "title": "Zimbabwe plans 600 MW floating PV project",
      "url": "https://www.pv-magazine.com/2025/12/11/zimbabwe-plans-600-mw-floating-pv-project/",
      "date": "2025-12-11T10:47:51.000Z",
      "source": "PV Magazine (Markets & Policy)",
      "bucket": "A"
    },
    {
      "title": "AX Solar Robot showcases cleaning system for C&#038;I solar",
      "url": "https://www.pv-magazine.com/2025/12/11/ax-solar-robot-showcases-cleaning-system-for-ci-solar/",
      "date": "2025-12-11T10:44:11.000Z",
      "source": "PV Magazine (Markets & Policy)",
      "bucket": "A"
    },
    {
      "title": "EU shift to 15-minute trading supports battery storage profits, says Rystad",
      "url": "https://www.pv-magazine.com/2025/12/11/eu-shift-to-15-minute-trading-supports-battery-storage-profits-says-rystad/",
      "date": "2025-12-11T10:15:53.000Z",
      "source": "PV Magazine (Markets & Policy)",
      "bucket": "A"
    },
    {
      "title": "Battery storage assets in Europe could see 3% ROI uplift with 15-minute trading, Rystad says",
      "url": "https://www.energy-storage.news/battery-storage-assets-in-europe-could-see-3-roi-uplift-with-15-minute-trading-rystad-says/",
      "date": "2025-12-11T09:31:41.000Z",
      "source": "Energy Storage News",
      "bucket": "A"
    },
    {
      "title": "Beijing group creates official entity to guide China’s polysilicon capacity",
      "url": "https://www.pv-magazine.com/2025/12/11/beijing-group-creates-official-body-to-guide-chinas-polysilicon-capacity/",
      "date": "2025-12-11T09:12:28.000Z",
      "source": "PV Magazine (Markets & Policy)",
      "bucket": "A"
    },
    {
      "title": "Solinteg releases new hybrid inverter series",
      "url": "https://www.pv-magazine.com/2025/12/11/solinteg-releases-new-hybrid-inverter-series/",
      "date": "2025-12-11T08:37:29.000Z",
      "source": "PV Magazine (Markets & Policy)",
      "bucket": "A"
    },
    {
      "title": "India’s Waaree Energies posts monthly solar module output above 1 GW",
      "url": "https://www.pv-magazine.com/2025/12/11/indias-waaree-energies-posts-monthly-solar-module-output-above-1-gw/",
      "date": "2025-12-11T08:30:15.000Z",
      "source": "PV Magazine (Markets & Policy)",
      "bucket": "A"
    },
    {
      "title": "California study finds electrification can ease electric rate pressures",
      "url": "https://www.pv-magazine.com/2025/12/11/california-study-finds-electrification-can-ease-electric-rate-pressures/",
      "date": "2025-12-11T07:45:50.000Z",
      "source": "PV Magazine (Markets & Policy)",
      "bucket": "A"
    },
    {
      "title": "ACWA Power, Scatec sign gigawatt-scale MENA solar-plus-storage project deals",
      "url": "https://www.energy-storage.news/acwa-power-scatec-sign-gigawatt-scale-mena-solar-plus-storage-project-deals/",
      "date": "2025-12-11T05:57:58.000Z",
      "source": "Energy Storage News",
      "bucket": "A"
    },
    {
      "title": "European Commission publishes new grid rules and plans to accelerate interconnection projects",
      "url": "https://www.pv-magazine.com/2025/12/10/european-commission-publishes-new-grid-rules-and-plans-to-accelerate-interconnection-projects/",
      "date": "2025-12-10T16:50:32.000Z",
      "source": "PV Magazine (Markets & Policy)",
      "bucket": "A"
    },
    {
      "title": "GCL Technology forms $287 million entity to buy stake in Chinese rival",
      "url": "https://www.pv-magazine.com/2025/12/10/gcl-technology-launches-287-million-partnership-for-stake-in-silicon-producer/",
      "date": "2025-12-10T16:30:32.000Z",
      "source": "PV Magazine (Markets & Policy)",
      "bucket": "A"
    },
    {
      "title": "Snapsun introduces rooftop mounting system made of recycled plastic",
      "url": "https://www.pv-magazine.com/2025/12/10/snapsun-introduces-rooftop-mounting-system-made-of-recycled-plastic/",
      "date": "2025-12-10T15:35:06.000Z",
      "source": "PV Magazine (Markets & Policy)",
      "bucket": "A"
    },
    {
      "title": "DMEGC launches framed solar module weighing 7.5 kg/m2",
      "url": "https://www.pv-magazine.com/2025/12/10/dmegc-launches-framed-solar-module-weighing-7-5-kg-m2/",
      "date": "2025-12-10T15:05:32.000Z",
      "source": "PV Magazine (Markets & Policy)",
      "bucket": "A"
    },
    {
      "title": "Poland shortlists 183 energy storage projects for EU funding",
      "url": "https://www.pv-magazine.com/2025/12/10/poland-shortlists-183-energy-storage-projects-for-eu-funding/",
      "date": "2025-12-10T14:05:55.000Z",
      "source": "PV Magazine (Markets & Policy)",
      "bucket": "A"
    },
    {
      "title": "Renolit showcases reflecting cool roof membrane for bifacial rooftop PV",
      "url": "https://www.pv-magazine.com/2025/12/10/renolit-showcases-reflecting-cool-roof-membrane-for-bifacial-rooftop-pv/",
      "date": "2025-12-10T13:52:46.000Z",
      "source": "PV Magazine (Markets & Policy)",
      "bucket": "A"
    },
    {
      "title": "France&#8217;s S&#8217;tile offers custom PV modules for repowering, revamping",
      "url": "https://www.pv-magazine.com/2025/12/10/frances-stile-offers-custom-pv-modules-for-repowering-revamping/",
      "date": "2025-12-10T13:16:45.000Z",
      "source": "PV Magazine (Markets & Policy)",
      "bucket": "A"
    },
    {
      "title": "NextEra signs 2.5GW of renewable energy agreements with Meta for projects across US",
      "url": "https://www.energy-storage.news/nextera-signs-2-5gw-of-renewable-energy-agreements-with-meta-for-projects-across-us/",
      "date": "2025-12-10T13:15:58.000Z",
      "source": "Energy Storage News",
      "bucket": "A"
    },
    {
      "title": "Clearway negotiates 560MWh tolling agreements with California IOU SDG&#038;E, sells BESS to yieldco",
      "url": "https://www.energy-storage.news/clearway-negotiates-560mwh-tolling-agreements-with-california-iou-sdge-sells-bess-to-yieldco/",
      "date": "2025-12-10T11:42:03.000Z",
      "source": "Energy Storage News",
      "bucket": "A"
    },
    {
      "title": "Submissions rebound in UK BESS development market in November",
      "url": "https://www.energy-storage.news/submissions-rebound-in-uk-bess-development-market-in-november/",
      "date": "2025-12-10T09:58:15.000Z",
      "source": "Energy Storage News",
      "bucket": "A"
    },
    {
      "title": "Engie hires former subsidiary NHOA Energy for 320MWh Belgium battery storage project",
      "url": "https://www.energy-storage.news/engie-hires-former-subsidiary-nhoa-energy-for-320mwh-belgium-battery-storage-project/",
      "date": "2025-12-10T09:53:06.000Z",
      "source": "Energy Storage News",
      "bucket": "A"
    },
    {
      "title": "Cape Verde welcomes wind and batteries that bring African island nation to nearly one-third renewable energy share",
      "url": "https://www.energy-storage.news/cape-verde-welcomes-wind-and-batteries-that-bring-african-island-nation-to-nearly-one-third-renewable-energy-share/",
      "date": "2025-12-10T09:51:27.000Z",
      "source": "Energy Storage News",
      "bucket": "A"
    },
    {
      "title": "Li-ion battery pack prices fell 8% since last year despite metals prices rising, BloombergNEF says",
      "url": "https://www.energy-storage.news/li-ion-battery-pack-prices-fell-8-since-last-year-despite-metals-prices-rising-bloombergnef-says/",
      "date": "2025-12-10T09:41:17.000Z",
      "source": "Energy Storage News",
      "bucket": "A"
    },
    {
      "title": "ROUNDUP: Energy Vault enters Switzerland, ZincFive raises funds, Convergent closes on NYC financing",
      "url": "https://www.energy-storage.news/roundup-energy-vault-enters-switzerland-zincfive-raises-funds-convergent-closes-on-nyc-financing/",
      "date": "2025-12-09T15:15:09.000Z",
      "source": "Energy Storage News",
      "bucket": "A"
    },
    {
      "title": "1.6GWh Melbourne Renewable Energy Hub battery storage system brought online in Australia",
      "url": "https://www.energy-storage.news/1-6gwh-melbourne-renewable-energy-hub-battery-storage-system-brought-online-in-australia/",
      "date": "2025-12-09T10:37:22.000Z",
      "source": "Energy Storage News",
      "bucket": "A"
    },
    {
      "title": "UK: ‘Painful but necessary’ reforms see 153GW of battery storage projects cut from grid connection queue",
      "url": "https://www.energy-storage.news/uk-painful-but-necessary-reforms-see-153gw-of-battery-storage-projects-cut-from-grid-connection-queue/",
      "date": "2025-12-09T09:41:04.000Z",
      "source": "Energy Storage News",
      "bucket": "A"
    },
    {
      "title": "Long-duration energy storage is non-negotiable for Europe&#8217;s energy transformation",
      "url": "https://www.energy-storage.news/long-duration-energy-storage-is-non-negotiable-for-europes-energy-transformation/",
      "date": "2025-12-09T09:22:48.000Z",
      "source": "Energy Storage News",
      "bucket": "A"
    },
    {
      "title": "Vena Energy signs BESS agreement with CATL for Indonesia-Singapore ‘renewable energy corridor’",
      "url": "https://www.energy-storage.news/vena-energy-signs-bess-agreement-with-catl-for-indonesia-singapore-renewable-energy-corridor/",
      "date": "2025-12-09T07:57:35.000Z",
      "source": "Energy Storage News",
      "bucket": "A"
    },
    {
      "title": "Western Australia’s 500MWh vanadium flow battery initiative is a ‘pivotal moment’",
      "url": "https://www.energy-storage.news/western-australias-500mwh-vanadium-flow-battery-initiative-is-a-pivotal-moment/",
      "date": "2025-12-09T01:07:00.000Z",
      "source": "Energy Storage News",
      "bucket": "A"
    },
    {
      "title": "Arizona county supervisors approve 400MWh BESS project near site of 2019 Surprise fire",
      "url": "https://www.energy-storage.news/arizona-county-supervisors-approve-400mwh-bess-project-near-site-of-2019-surprise-fire/",
      "date": "2025-12-08T16:39:15.000Z",
      "source": "Energy Storage News",
      "bucket": "A"
    },
    {
      "title": "Desert Mountain Energy plans sodium nickel chloride battery factory in New Mexico",
      "url": "https://www.energy-storage.news/desert-mountain-energy-plans-sodium-nickel-chloride-battery-factory-in-new-mexico/",
      "date": "2025-12-08T14:28:22.000Z",
      "source": "Energy Storage News",
      "bucket": "A"
    },
    {
      "title": "Angola: Energy minister inaugurates first solar-plus-storage minigrid in national rollout",
      "url": "https://www.energy-storage.news/angola-first-solar-plus-storage-minigrid-national-rollout/",
      "date": "2025-12-08T13:59:15.000Z",
      "source": "Energy Storage News",
      "bucket": "A"
    },
    {
      "title": "Vena Energy builds 408MWh BESS at third phase of South Australia renewable energy project",
      "url": "https://www.energy-storage.news/vena-energy-builds-408mwh-bess-at-third-phase-of-south-australia-renewable-energy-project/",
      "date": "2025-12-08T08:28:37.000Z",
      "source": "Energy Storage News",
      "bucket": "A"
    },
    {
      "title": "BrightNight and Cordelio close on 800MWh Washington state BESS",
      "url": "https://www.energy-storage.news/brightnight-and-cordelio-close-on-800mwh-washington-state-bess/",
      "date": "2025-12-05T11:24:00.000Z",
      "source": "Energy Storage News",
      "bucket": "A"
    },
    {
      "title": "ADS-TEC battery-buffered EV fast chargers put into ancillary services market in Austria",
      "url": "https://www.energy-storage.news/ads-tec-battery-buffered-ev-fast-chargers-put-into-ancillary-services-market-in-austria/",
      "date": "2025-12-05T09:16:16.000Z",
      "source": "Energy Storage News",
      "bucket": "A"
    },
    {
      "title": "Australia&#8217;s grid-forming battery storage pipeline extends to nearly a hundred projects, says AEMO",
      "url": "https://www.energy-storage.news/australias-grid-forming-battery-storage-pipeline-extends-to-nearly-a-hundred-projects-says-aemo/",
      "date": "2025-12-05T05:30:54.000Z",
      "source": "Energy Storage News",
      "bucket": "A"
    },
    {
      "title": "RWE commissions Texas solar-plus-storage project",
      "url": "https://www.energy-storage.news/rwe-commissions-texas-solar-plus-storage-project/",
      "date": "2025-12-04T15:31:37.000Z",
      "source": "Energy Storage News",
      "bucket": "A"
    },
    {
      "title": "Indiana utility to deliver 1.6GWh BESS for Amazon’s data center expansion, though fossil fuels form major part of package",
      "url": "https://www.energy-storage.news/indiana-utility-to-deliver-1-6gwh-bess-for-amazons-data-center-expansion-though-fossil-fuels-form-major-part-of-package/",
      "date": "2025-12-04T15:16:06.000Z",
      "source": "Energy Storage News",
      "bucket": "A"
    },
    {
      "title": "PJM awards interconnection agreements to 23 BESS resources",
      "url": "https://www.energy-storage.news/pjm-awards-interconnection-agreements-to-23-bess-resources/",
      "date": "2025-12-04T13:31:10.000Z",
      "source": "Energy Storage News",
      "bucket": "A"
    },
    {
      "title": "Germany Roundup: 500MW BESS and data centre transaction, seven-year toll and 370MW pipeline secured",
      "url": "https://www.energy-storage.news/germany-roundup-500mw-bess-and-data-centre-transaction-seven-year-toll-and-370mw-pipeline-secured/",
      "date": "2025-12-04T12:06:13.000Z",
      "source": "Energy Storage News",
      "bucket": "A"
    },
    {
      "title": "Eight energy trends that will shape Australian energy storage in 2026",
      "url": "https://www.energy-storage.news/eight-energy-trends-that-will-shape-energy-storage-in-2026/",
      "date": "2025-12-04T03:00:00.000Z",
      "source": "Energy Storage News",
      "bucket": "A"
    },
    {
      "title": "Zenith locks in 25-year PPA for 300MWh hybrid storage project at Western Australia gold mine",
      "url": "https://www.energy-storage.news/zenith-locks-in-25-year-ppa-for-300mwh-hybrid-storage-project-at-western-australia-gold-mine/",
      "date": "2025-12-04T02:00:00.000Z",
      "source": "Energy Storage News",
      "bucket": "A"
    },
    {
      "title": "ABB acquires Gamesa Electric power electronics division for undisclosed sum",
      "url": "https://www.energy-storage.news/abb-acquires-gamesa-electric-power-electronics-division-for-undisclosed-sum/",
      "date": "2025-12-03T13:51:40.000Z",
      "source": "Energy Storage News",
      "bucket": "A"
    },
    {
      "title": "Ontario municipality denies support for 3.2GWh BESS project ahead of looming IESO RFP deadline",
      "url": "https://www.energy-storage.news/ontario-municipality-denies-support-for-3-2gwh-bess-project-ahead-of-looming-ieso-rfp-deadline/",
      "date": "2025-12-03T12:56:32.000Z",
      "source": "Energy Storage News",
      "bucket": "A"
    },
    {
      "title": "Cache Power plans ‘Canada’s first’ commercial-scale compressed air energy storage facility",
      "url": "https://www.energy-storage.news/cache-power-plans-canadas-first-commercial-scale-compressed-air-energy-storage-facility/",
      "date": "2025-12-03T12:38:23.000Z",
      "source": "Energy Storage News",
      "bucket": "A"
    },
    {
      "title": "State-owned Stanwell bags exclusivity for Quinbrook’s 6.24GWh hybrid energy storage facility in Australia",
      "url": "https://www.energy-storage.news/state-owned-stanwell-bags-exclusivity-for-quinbrooks-6-24gwh-hybrid-energy-storage-facility-in-australia/",
      "date": "2025-12-03T11:06:08.000Z",
      "source": "Energy Storage News",
      "bucket": "A"
    },
    {
      "title": "Are battery companies focusing on lithium-ion alternatives financially viable?",
      "url": "https://www.energy-storage.news/are-battery-companies-focusing-on-lithium-ion-alternatives-financially-viable/",
      "date": "2025-12-03T11:01:55.000Z",
      "source": "Energy Storage News",
      "bucket": "A"
    },
    {
      "title": "VIDEO: Powering certainty with Elementa 2 Pro, bankable energy storage from Trina",
      "url": "https://www.energy-storage.news/video-powering-certainty-with-elementa-2-pro-bankable-energy-storage-from-trina/",
      "date": "2025-12-03T10:26:46.000Z",
      "source": "Energy Storage News",
      "bucket": "A"
    },
    {
      "title": "FRV and AGL advance 2,200MWh of grid-forming battery energy storage in Australia",
      "url": "https://www.energy-storage.news/frv-and-agl-advance-2200mwh-of-grid-forming-battery-energy-storage-in-australia/",
      "date": "2025-12-03T00:00:00.000Z",
      "source": "Energy Storage News",
      "bucket": "A"
    },
    {
      "title": "Aypa Power to build, own, and operate 1,200MWh South Carolina BESS",
      "url": "https://www.energy-storage.news/aypa-power-to-build-own-and-operate-1200mwh-south-carolina-bess/",
      "date": "2025-12-02T14:00:20.000Z",
      "source": "Energy Storage News",
      "bucket": "A"
    },
    {
      "title": "US battery manufacturing &#8216;could cover domestic BESS demand within a few years&#8217;",
      "url": "https://www.energy-storage.news/us-battery-manufacturing-could-cover-domestic-bess-demand-within-a-few-years/",
      "date": "2025-12-02T12:00:32.000Z",
      "source": "Energy Storage News",
      "bucket": "A"
    },
    {
      "title": "Puerto Rico advances on its delayed accelerated BESS deployment programme",
      "url": "https://www.energy-storage.news/puerto-rico-advances-on-its-delayed-accelerated-bess-deployment-programme/",
      "date": "2025-12-02T11:50:26.000Z",
      "source": "Energy Storage News",
      "bucket": "A"
    },
    {
      "title": "HDRE, Brawn Capital put ‘100% merchant’ BESS into operation in northern Japan",
      "url": "https://www.energy-storage.news/hdre-brawn-capital-put-100-merchant-bess-into-operation-in-northern-japan/",
      "date": "2025-12-02T10:53:10.000Z",
      "source": "Energy Storage News",
      "bucket": "A"
    },
    {
      "title": "World Bank supports multi-gigawatt cross-border renewable energy project in Malaysia",
      "url": "https://www.energy-storage.news/world-bank-supports-multi-gigawatt-cross-border-renewable-energy-project-in-malaysia/",
      "date": "2025-12-02T09:04:35.000Z",
      "source": "Energy Storage News",
      "bucket": "A"
    },
    {
      "title": "Fortescue deploys 250MWh BYD battery system in Western Australia",
      "url": "https://www.energy-storage.news/fortescue-deploys-250mwh-byd-battery-system-in-western-australia/",
      "date": "2025-12-01T23:00:00.000Z",
      "source": "Energy Storage News",
      "bucket": "A"
    },
    {
      "title": "&#8216;Italy is a natural market for batteries&#8217;: Greenvolt Power on its MACSE-winning project",
      "url": "https://www.energy-storage.news/italy-is-a-natural-market-for-batteries-greenvolt-power-on-its-macse-winning-project/",
      "date": "2025-12-01T12:25:09.000Z",
      "source": "Energy Storage News",
      "bucket": "A"
    },
    {
      "title": "Skeleton Tech begins manufacturing high-power solutions to AI boom in Europe",
      "url": "https://www.energy-storage.news/skeleton-tech-begins-manufacturing-high-power-solutions-to-ai-boom-in-europe/",
      "date": "2025-12-01T12:16:40.000Z",
      "source": "Energy Storage News",
      "bucket": "A"
    },
    {
      "title": "Multiple gigawatts of European BESS project M&#038;A, financing and route-to-market deals",
      "url": "https://www.energy-storage.news/multiple-gigawatts-of-european-bess-project-ma-financing-and-route-to-market-deals/",
      "date": "2025-12-01T12:05:56.000Z",
      "source": "Energy Storage News",
      "bucket": "A"
    },
    {
      "title": "600MWh Bulabul battery storage site in Australia attracts Danish partner in AU$300 million deal",
      "url": "https://www.energy-storage.news/600mwh-bulabul-battery-storage-site-in-australia-attracts-danish-partner-in-au300-million-deal/",
      "date": "2025-11-30T00:00:00.000Z",
      "source": "Energy Storage News",
      "bucket": "A"
    },
    {
      "title": "Battery storage fire safety: Sungrow, Wärtsilä, Chint Power products put through LSFT",
      "url": "https://www.energy-storage.news/battery-storage-fire-safety-sungrow-wartsila-chint-power-products-put-through-lsft/",
      "date": "2025-11-28T12:37:17.000Z",
      "source": "Energy Storage News",
      "bucket": "A"
    },
    {
      "title": "Australia opens Capacity Investment Scheme Tender 8, seeking 16GWh of energy storage across NEM",
      "url": "https://www.energy-storage.news/australia-opens-capacity-investment-scheme-tender-8-seeking-16gwh-of-energy-storage-across-nem/",
      "date": "2025-11-28T12:36:20.000Z",
      "source": "Energy Storage News",
      "bucket": "A"
    },
    {
      "title": "Michigan Township enacts one-year BESS moratorium after greenfield developer sizes up area for utility-scale project",
      "url": "https://www.energy-storage.news/michigan-township-enacts-one-year-bess-moratorium-after-greenfield-developer-sizes-up-area-for-utility-scale-project/",
      "date": "2025-11-28T11:04:34.000Z",
      "source": "Energy Storage News",
      "bucket": "A"
    }
  ]
}